README.md
setup.py
jax_tools/__init__.py
jax_tools/colorful_font.py
jax_tools/encrypt.py
jax_tools/logger.py
jax_tools/network_test.py
jax_tools/proxies.py
jax_tools/ps.py
jax_tools/ssh.py
jax_tools.egg-info/PKG-INFO
jax_tools.egg-info/SOURCES.txt
jax_tools.egg-info/dependency_links.txt
jax_tools.egg-info/entry_points.txt
jax_tools.egg-info/requires.txt
jax_tools.egg-info/top_level.txt
jax_tools/cmd/__init__.py
jax_tools/cmd/build_pip.py
jax_tools/cmd/install_python.py
jax_tools/cmd/jax.py
jax_tools/cmd/jax_csv_to_xlsx.py
jax_tools/cmd/jax_encrypt.py
jax_tools/cmd/jax_find.py
jax_tools/cmd/jax_fix.py
jax_tools/cmd/jax_gpt.py
jax_tools/cmd/jax_nd.py
jax_tools/cmd/jax_pam.py
jax_tools/cmd/jax_tail.py
jax_tools/cmd/jax_xargs.py
jax_tools/cmd/nd.py
jax_tools/cmd/pgp_tool.py
jax_tools/cmd/upgrade_pip.py
jax_tools/cmd_tools/__init__.py
jax_tools/cmd_tools/pam.py
jax_tools/sec/__init__.py
jax_tools/sec/verify.py
jax_tools/tools/__init__.py
jax_tools/tools/command.py
jax_tools/tools/common_work_tools.py
jax_tools/utils/__init__.py
jax_tools/utils/base.py
jax_tools/utils/settings.py