Metadata-Version: 2.1
Name: jax-tools
Version: 1.0.184
Summary: Jax common tools library
Home-page: https://jax-arsenals.com
Author: Jax
Author-email: alvin.wan.cn@hotmail.com
License: MIT Licence
Download-URL: https://jax-arsenals.com
Keywords: jax
Platform: CentOS
Platform: Redhat
Platform: MacOS
Platform: Windows
Requires-Python: >=3.0.0
Provides-Extra: win10
Provides-Extra: openai
Provides-Extra: python
